spinnaker_testbase/__init__.py
spinnaker_testbase/_version.py
spinnaker_testbase/base_test_case.py
spinnaker_testbase/ping.py
spinnaker_testbase/py.typed
spinnaker_testbase/root_script_builder.py
spinnaker_testbase/root_test_case.py
spinnaker_testbase/script_checker.py
spinnaker_testbase/test_no_job_destroy.py
spinnaker_testbase/test_scripts_header
spinnakertestbase-1!7.4.1.dist-info/licenses/LICENSE
spinnakertestbase-1!7.4.1.dist-info/licenses/LICENSE_POLICY.md
spinnakertestbase-1!7.4.1.dist-info/METADATA
spinnakertestbase-1!7.4.1.dist-info/WHEEL
spinnakertestbase-1!7.4.1.dist-info/top_level.txt
spinnakertestbase-1!7.4.1.dist-info/zip-safe
spinnakertestbase-1!7.4.1.dist-info/RECORD
